MANIFEST.in
README.markdown
dev-requirements.txt
setup.py
snapshotter/__init__.py
snapshotter/snapshotter.py
snapshotter/test_snapshotter.py
snapshotter.egg-info/PKG-INFO
snapshotter.egg-info/SOURCES.txt
snapshotter.egg-info/dependency_links.txt
snapshotter.egg-info/entry_points.txt
snapshotter.egg-info/top_level.txt
snapshotter/test_data/one.txt
snapshotter/test_data/two.markdown