Metadata-Version: 1.1
Name: snapshotter
Version: 1.0.1
Summary: Very easy incremental snapshot backups using rsync
Home-page: https://github.com/seanh/snapshotter
Author: Sean Hammond
Author-email: snapshotter@seanh.cc
License: GPLv3
Platform: UNKNOWN
Classifier: Development Status :: 4 - Beta
Classifier: License :: OSI Approved :: GNU General Public License v3 (GPLv3)
Classifier: Programming Language :: Python :: 2.7
